{"AIPlayer":[
	{	"ID":"1",	"RefIcon":"1",	"VipLevel":"3"},
	{	"ID":"2",	"RefIcon":"2",	"VipLevel":"3"},
	{	"ID":"3",	"RefIcon":"3",	"VipLevel":"3"},
	{	"ID":"4",	"RefIcon":"4",	"VipLevel":"4"},
	{	"ID":"5",	"RefIcon":"5",	"VipLevel":"4"},
	{	"ID":"6",	"RefIcon":"6",	"VipLevel":"4"},
	{	"ID":"7",	"RefIcon":"7",	"VipLevel":"5"},
	{	"ID":"8",	"RefIcon":"8",	"VipLevel":"5"},
	{	"ID":"9",	"RefIcon":"9",	"VipLevel":"6"},
	{	"ID":"10",	"RefIcon":"10",	"VipLevel":"7"},
	{	"ID":"11",	"RefIcon":"11",	"VipLevel":"3"},
	{	"ID":"12",	"RefIcon":"12",	"VipLevel":"3"},
	{	"ID":"13",	"RefIcon":"13",	"VipLevel":"3"},
	{	"ID":"14",	"RefIcon":"14",	"VipLevel":"4"},
	{	"ID":"15",	"RefIcon":"15",	"VipLevel":"4"},
	{	"ID":"16",	"RefIcon":"16",	"VipLevel":"4"},
	{	"ID":"17",	"RefIcon":"17",	"VipLevel":"5"},
	{	"ID":"18",	"RefIcon":"18",	"VipLevel":"5"},
	{	"ID":"19",	"RefIcon":"19",	"VipLevel":"6"},
	{	"ID":"20",	"RefIcon":"20",	"VipLevel":"7"},
	{	"ID":"21",	"RefIcon":"21",	"VipLevel":"3"},
	{	"ID":"22",	"RefIcon":"1",	"VipLevel":"3"},
	{	"ID":"23",	"RefIcon":"2",	"VipLevel":"3"},
	{	"ID":"24",	"RefIcon":"3",	"VipLevel":"3"},
	{	"ID":"25",	"RefIcon":"4",	"VipLevel":"5"},
	{	"ID":"26",	"RefIcon":"5",	"VipLevel":"3"},
	{	"ID":"27",	"RefIcon":"6",	"VipLevel":"3"},
	{	"ID":"28",	"RefIcon":"7",	"VipLevel":"3"},
	{	"ID":"29",	"RefIcon":"8",	"VipLevel":"3"},
	{	"ID":"30",	"RefIcon":"9",	"VipLevel":"4"},
	{	"ID":"31",	"RefIcon":"10",	"VipLevel":"3"},
	{	"ID":"32",	"RefIcon":"18",	"VipLevel":"3"},
	{	"ID":"33",	"RefIcon":"19",	"VipLevel":"3"},
	{	"ID":"34",	"RefIcon":"20",	"VipLevel":"3"},
	{	"ID":"35",	"RefIcon":"21",	"VipLevel":"3"},
	{	"ID":"36",	"RefIcon":"22",	"VipLevel":"3"},
	{	"ID":"37",	"RefIcon":"23",	"VipLevel":"3"},
	{	"ID":"38",	"RefIcon":"24",	"VipLevel":"3"},
	{	"ID":"39",	"RefIcon":"25",	"VipLevel":"3"},
	{	"ID":"40",	"RefIcon":"26",	"VipLevel":"3"},
	{	"ID":"41",	"RefIcon":"27",	"VipLevel":"3"},
	{	"ID":"42",	"RefIcon":"28",	"VipLevel":"3"},
	{	"ID":"43",	"RefIcon":"29",	"VipLevel":"3"},
	{	"ID":"44",	"RefIcon":"30",	"VipLevel":"3"},
	{	"ID":"45",	"RefIcon":"31",	"VipLevel":"3"},
	{	"ID":"46",	"RefIcon":"18",	"VipLevel":"3"},
	{	"ID":"47",	"RefIcon":"19",	"VipLevel":"3"},
	{	"ID":"48",	"RefIcon":"20",	"VipLevel":"3"},
	{	"ID":"49",	"RefIcon":"21",	"VipLevel":"3"},
	{	"ID":"50",	"RefIcon":"22",	"VipLevel":"3"},
	{	"ID":"51",	"RefIcon":"23",	"VipLevel":"3"},
	{	"ID":"52",	"RefIcon":"24",	"VipLevel":"3"},
	{	"ID":"53",	"RefIcon":"25",	"VipLevel":"3"},
	{	"ID":"54",	"RefIcon":"26",	"VipLevel":"3"},
	{	"ID":"55",	"RefIcon":"27",	"VipLevel":"3"},
	{	"ID":"56",	"RefIcon":"28",	"VipLevel":"4"},
	{	"ID":"57",	"RefIcon":"29",	"VipLevel":"4"},
	{	"ID":"58",	"RefIcon":"30",	"VipLevel":"4"},
	{	"ID":"59",	"RefIcon":"31",	"VipLevel":"4"},
	{	"ID":"60",	"RefIcon":"18",	"VipLevel":"4"},
	{	"ID":"61",	"RefIcon":"19",	"VipLevel":"4"},
	{	"ID":"62",	"RefIcon":"20",	"VipLevel":"4"},
	{	"ID":"63",	"RefIcon":"21",	"VipLevel":"4"},
	{	"ID":"64",	"RefIcon":"22",	"VipLevel":"4"},
	{	"ID":"65",	"RefIcon":"23",	"VipLevel":"4"},
	{	"ID":"66",	"RefIcon":"24",	"VipLevel":"4"},
	{	"ID":"67",	"RefIcon":"25",	"VipLevel":"5"},
	{	"ID":"68",	"RefIcon":"26",	"VipLevel":"5"},
	{	"ID":"69",	"RefIcon":"27",	"VipLevel":"5"},
	{	"ID":"70",	"RefIcon":"28",	"VipLevel":"5"},
	{	"ID":"71",	"RefIcon":"29",	"VipLevel":"5"},
	{	"ID":"72",	"RefIcon":"30",	"VipLevel":"5"},
	{	"ID":"73",	"RefIcon":"31",	"VipLevel":"5"},
	{	"ID":"74",	"RefIcon":"18",	"VipLevel":"5"},
	{	"ID":"75",	"RefIcon":"19",	"VipLevel":"6"},
	{	"ID":"76",	"RefIcon":"20",	"VipLevel":"6"},
	{	"ID":"77",	"RefIcon":"21",	"VipLevel":"6"},
	{	"ID":"78",	"RefIcon":"22",	"VipLevel":"6"},
	{	"ID":"79",	"RefIcon":"23",	"VipLevel":"7"},
	{	"ID":"80",	"RefIcon":"24",	"VipLevel":"7"}
]}